{
    "Ar36": {
        "error": 0.0025238605715442479, 
        "fit": "parabolic", 
        "value": 0.032432126120832377
    }, 
    "Ar37": {
        "error": 0.13504524496889042, 
        "fit": "linear", 
        "value": -0.087141741586132596
    }, 
    "Ar38": {
        "error": 0.14526747248798069, 
        "fit": "linear", 
        "value": 1.2273080578485125
    }, 
    "Ar39": {
        "error": 0.11243568393678795, 
        "fit": "parabolic", 
        "value": 110.95001068451421
    }, 
    "Ar40": {
        "error": 0.50012351965546464, 
        "fit": "parabolic", 
        "value": 1532.3294106782746
    }, 
    "Ar41": {
        "error": 0.13872162265955482, 
        "fit": "average_SEM", 
        "value": -0.069044446615735069
    }
}