{
    "AX": {
        "error": 0.054952136608780094, 
        "fit": "average_SEM", 
        "value": -0.003996825778691952
    }, 
    "CDD": {
        "error": 0.00013963302754297968, 
        "fit": "average_SEM", 
        "value": 0.00011789761047111824
    }, 
    "H1": {
        "error": 0.13507905716971746, 
        "fit": "average_SEM", 
        "value": 0.05121496628271416
    }, 
    "H2": {
        "error": 0.11373917563283518, 
        "fit": "average_SEM", 
        "value": 0.23209022233301463
    }, 
    "L1": {
        "error": 0.1449512600510899, 
        "fit": "average_SEM", 
        "value": -0.0835403716249857
    }, 
    "L2": {
        "error": 0.13153038698014255, 
        "fit": "average_SEM", 
        "value": -0.048337906178009385
    }
}