{
    "AX": {
        "error": 0.06443578505591821, 
        "fit": "average_SEM", 
        "value": -0.00993201163073536
    }, 
    "CDD": {
        "error": 2.802462017628634e-05, 
        "fit": "average_SEM", 
        "value": 5.182312452234328e-06
    }, 
    "H1": {
        "error": 0.1169934741452497, 
        "fit": "average_SEM", 
        "value": -0.031749122915789484
    }, 
    "H2": {
        "error": 0.14598199074990156, 
        "fit": "average_SEM", 
        "value": -0.015892827997837835
    }, 
    "L1": {
        "error": 0.13195283962779197, 
        "fit": "average_SEM", 
        "value": -0.07120628815270418
    }, 
    "L2": {
        "error": 0.14012440132575885, 
        "fit": "average_SEM", 
        "value": 0.009430439810057579
    }
}