{
    "AX": {
        "error": 0.05722841942005806, 
        "fit": "average_SEM", 
        "value": -0.051319350040284914
    }, 
    "CDD": {
        "error": 3.659055414416811e-05, 
        "fit": "average_SEM", 
        "value": 9.069046791410074e-06
    }, 
    "H1": {
        "error": 0.1359777584137866, 
        "fit": "average_SEM", 
        "value": 0.01969508895999752
    }, 
    "H2": {
        "error": 0.13531192698015682, 
        "fit": "average_SEM", 
        "value": -0.0980103529873304
    }, 
    "L1": {
        "error": 0.17298235230945005, 
        "fit": "average_SEM", 
        "value": -0.07455347096450472
    }, 
    "L2": {
        "error": 0.13452114575836568, 
        "fit": "average_SEM", 
        "value": 0.025033829830742132
    }
}