{
    "Ar36": {
        "error": 0.0018862165373789478, 
        "fit": "linear", 
        "value": 0.014195002118614658
    }, 
    "Ar37": {
        "error": 0.14166341219614523, 
        "fit": "linear", 
        "value": -0.021806870737879833
    }, 
    "Ar38": {
        "error": 0.1744708263926964, 
        "fit": "linear", 
        "value": 0.20473470492315726
    }, 
    "Ar39": {
        "error": 0.0697553631147734, 
        "fit": "linear", 
        "value": 22.545424771570026
    }, 
    "Ar40": {
        "error": 0.43463134305937351, 
        "fit": "linear", 
        "value": 1383.1552086311967
    }, 
    "Ar41": {
        "error": 0.11879739555967579, 
        "fit": "average_SEM", 
        "value": -0.34415679607126448
    }
}