{
    "Ar36": {
        "error": 0.0018225846264090797, 
        "fit": "parabolic", 
        "value": 0.010447640406778274
    }, 
    "Ar37": {
        "error": 0.14256349047842334, 
        "fit": "linear", 
        "value": -0.041432339287941232
    }, 
    "Ar38": {
        "error": 0.21565319500632443, 
        "fit": "linear", 
        "value": 0.37231677589260248
    }, 
    "Ar39": {
        "error": 0.083416753970017132, 
        "fit": "parabolic", 
        "value": 35.441377863308077
    }, 
    "Ar40": {
        "error": 0.54335345003531776, 
        "fit": "parabolic", 
        "value": 2196.3392455046496
    }, 
    "Ar41": {
        "error": 0.13160829612124311, 
        "fit": "average_SEM", 
        "value": 0.28809492933796721
    }
}