{
    "AX": {
        "error": 0.05317305239086247, 
        "fit": "average_SEM", 
        "value": -0.027353780741234207
    }, 
    "CDD": {
        "error": 0.00013189497735424937, 
        "fit": "average_SEM", 
        "value": 0.00011228343743520478
    }, 
    "H1": {
        "error": 0.125723230641064, 
        "fit": "average_SEM", 
        "value": 0.09709107878152282
    }, 
    "H2": {
        "error": 0.14619597383197125, 
        "fit": "average_SEM", 
        "value": -0.12095325445859796
    }, 
    "L1": {
        "error": 0.12236871060368938, 
        "fit": "average_SEM", 
        "value": -0.17333929610645604
    }, 
    "L2": {
        "error": 0.137328707793417, 
        "fit": "average_SEM", 
        "value": -0.13048680292752882
    }
}